quora/__init__.py
quora/__main__.py
quora/_parsers.py
quora/answer.py
quora/cache.py
quora/content.py
quora/exceptions.py
quora/profile.py
quora/question.py
quora/sync.py
quora/topic.py
quora/user.py
pyquora-0.4.4.dist-info/LICENSE
pyquora-0.4.4.dist-info/METADATA
pyquora-0.4.4.dist-info/WHEEL
pyquora-0.4.4.dist-info/top_level.txt
pyquora-0.4.4.dist-info/RECORD
