Metadata-Version: 2.1
Name: pyquora
Version: 0.4.4
Summary: Fetch profiles and data from Quora.
Home-page: https://github.com/TheShubhendra/pyquora
Author: Shubhendra Kushwaha
Author-email: shubhendrakushwaha94@gmail.com
License: MIT
Keywords: scraper,quora
Classifier: Development Status :: 4 - Beta
Classifier: Environment :: Console
Classifier: Intended Audience :: Developers
Classifier: Intended Audience :: End Users/Desktop
Classifier: Topic :: Software Development
Classifier: Topic :: Software Development :: Libraries
Classifier: License :: Free For Educational Use
Classifier: License :: Free For Home Use
Classifier: License :: OSI Approved :: MIT License
Classifier: Natural Language :: English
Classifier: Programming Language :: Python :: 3.7
Classifier: Programming Language :: Python :: 3.8
Classifier: Programming Language :: Python :: 3.9
Classifier: Programming Language :: Python :: 3.10
Classifier: Programming Language :: Python :: 3.11
Requires-Python: >=3.7
License-File: LICENSE
Requires-Dist: aiohttp[speedups]
